tgcrypto.cpython-310-darwin.so
tests/__init__.py
tests/ige/__init__.py
tests/ige/test_ige.py
tests/ctr/__init__.py
tests/ctr/test_ctr.py
tests/cbc/__init__.py
tests/cbc/test_cbc.py
mtprotocrypt-1.2.6.dist-info/RECORD
mtprotocrypt-1.2.6.dist-info/LICENSE
mtprotocrypt-1.2.6.dist-info/WHEEL
mtprotocrypt-1.2.6.dist-info/top_level.txt
mtprotocrypt-1.2.6.dist-info/METADATA
